Metadata-Version: 1.1
Name: DeleteExpiredFile
Version: 1.0.0
Summary: delete expired file with function or thread
Home-page: https://pypi.org/project/DeleteExpiredFile
Author: KuoYuan Li
Author-email: funny4875@gmail.com
License: UNKNOWN
Keywords: delete files,delete expired files,delete rountine
Platform: UNKNOWN
Classifier: License :: OSI Approved :: MIT License
Classifier: Programming Language :: Python :: 3.6
Classifier: Programming Language :: Python :: 3.7
Classifier: Programming Language :: Python :: 3.8
